{
 "workload": "euroc_MH_01_easy_inertial_slam__landmarks_export",
 "device": "dellworkstation_sm89",
 "adapter": "cuvslam",
 "source": "profiling/results/2026-07-07_224843_mav0_ncu_dellworkstation_sm89",
 "device_peaks": {
  "dram_gbps": 205.0,
  "peak_gflops": 5445.0,
  "hw": "dellworkstation_sm89.toml",
  "basis": "measured"
 },
 "qor": {
  "plain_ape_m": 0.6891,
  "nsys_ape_m": 0.6891,
  "ncu_ape_m": 0.6891
 },
 "note": "campaign cell (ncu quick window)",
 "stages": [],
 "kernels": [
  {
   "name": "cuvslam::reduced_system_stage_2_kernel",
   "stage": "?",
   "time_ms": 0.053,
   "share_pct": 25.42,
   "limiter": "memory-leaning",
   "substrate": "GPU-keep",
   "pim_affinity": "?",
   "rationale": "quick ncu window: coarse SoL split; deep verdict joined from the studies",
   "study": {
    "attribution": {
     "shared_pct": 3.9,
     "spill_pct": 0.0,
     "global_pct": 96.1,
     "data_structure": "ba_linear_system",
     "tag_agreement_pct": 100.0
    },
    "taxonomy_stability": {
     "modal_class": "G3",
     "n_seq": "27",
     "verdict": "consistent"
    },
    "kmeans": {
     "cluster_k8": "1",
     "sweep_best_k": "8"
    }
   },
   "evidence": {
    "dram_sol_pct": 37.57114,
    "sectors_per_req": null,
    "lfmr": null,
    "mpki": null,
    "occupancy_pct": null,
    "ai": null,
    "dominant_stall": ""
   },
   "sm_sol_pct": 30.748905,
   "roofline": null
  },
  {
   "name": "cuvslam::reduced_system_stage_12_kernel",
   "stage": "?",
   "time_ms": 0.024,
   "share_pct": 11.64,
   "limiter": "memory-leaning",
   "substrate": "GPU-keep",
   "pim_affinity": "?",
   "rationale": "quick ncu window: coarse SoL split; deep verdict joined from the studies",
   "study": {
    "attribution": {
     "shared_pct": 44.1,
     "spill_pct": 0.0,
     "global_pct": 55.9,
     "data_structure": "ba_linear_system",
     "tag_agreement_pct": 100.0
    },
    "taxonomy_stability": {
     "modal_class": "G0",
     "n_seq": "27",
     "verdict": "consistent"
    },
    "kmeans": {
     "cluster_k8": "1",
     "sweep_best_k": "8"
    }
   },
   "evidence": {
    "dram_sol_pct": 40.692714,
    "sectors_per_req": null,
    "lfmr": null,
    "mpki": null,
    "occupancy_pct": null,
    "ai": null,
    "dominant_stall": ""
   },
   "sm_sol_pct": 24.755021,
   "roofline": null
  },
  {
   "name": "cuvslam::reduced_system_stage_1_kernel",
   "stage": "?",
   "time_ms": 0.023,
   "share_pct": 11.04,
   "limiter": "memory-leaning",
   "substrate": "CPU/host",
   "pim_affinity": "?",
   "rationale": "quick ncu window: coarse SoL split; deep verdict joined from the studies",
   "study": {
    "attribution": {
     "shared_pct": 0.0,
     "spill_pct": 72.2,
     "global_pct": 27.8,
     "data_structure": "ba_linear_system",
     "tag_agreement_pct": 100.0
    },
    "taxonomy_stability": {
     "modal_class": "G7",
     "n_seq": "27",
     "verdict": "unanimous"
    },
    "kmeans": {
     "cluster_k8": "2",
     "sweep_best_k": "8"
    }
   },
   "evidence": {
    "dram_sol_pct": 44.896184,
    "sectors_per_req": null,
    "lfmr": null,
    "mpki": null,
    "occupancy_pct": null,
    "ai": null,
    "dominant_stall": ""
   },
   "sm_sol_pct": 18.993969,
   "roofline": null
  },
  {
   "name": "cuvslam::v1T_x_M_T_x_v2_kernel",
   "stage": "?",
   "time_ms": 0.017,
   "share_pct": 8.31,
   "limiter": "memory-leaning",
   "substrate": "PiM-near-bank",
   "pim_affinity": "?",
   "rationale": "quick ncu window: coarse SoL split; deep verdict joined from the studies",
   "study": {
    "attribution": {
     "shared_pct": 87.6,
     "spill_pct": 0.0,
     "global_pct": 12.4,
     "data_structure": "ba_linear_system",
     "tag_agreement_pct": 100.0
    },
    "taxonomy_stability": {
     "modal_class": "G1",
     "n_seq": "27",
     "verdict": "consistent"
    },
    "kmeans": {
     "cluster_k8": "5",
     "sweep_best_k": "8"
    }
   },
   "evidence": {
    "dram_sol_pct": 19.100233,
    "sectors_per_req": null,
    "lfmr": null,
    "mpki": null,
    "occupancy_pct": null,
    "ai": null,
    "dominant_stall": ""
   },
   "sm_sol_pct": 18.96699,
   "roofline": null
  },
  {
   "name": "cuvslam::reduce_abs_max_kernel",
   "stage": "?",
   "time_ms": 0.015,
   "share_pct": 7.43,
   "limiter": "memory-leaning",
   "substrate": "GPU-keep",
   "pim_affinity": "?",
   "rationale": "quick ncu window: coarse SoL split; deep verdict joined from the studies",
   "study": {
    "attribution": {
     "shared_pct": 14.8,
     "spill_pct": 0.0,
     "global_pct": 85.2,
     "data_structure": "ba_linear_system",
     "tag_agreement_pct": 100.0
    },
    "taxonomy_stability": {
     "modal_class": "G4",
     "n_seq": "27",
     "verdict": "consistent"
    },
    "kmeans": {
     "cluster_k8": "0",
     "sweep_best_k": "8"
    }
   },
   "evidence": {
    "dram_sol_pct": 0.90924,
    "sectors_per_req": null,
    "lfmr": null,
    "mpki": null,
    "occupancy_pct": null,
    "ai": null,
    "dominant_stall": ""
   },
   "sm_sol_pct": 0.205079,
   "roofline": null
  },
  {
   "name": "cuvslam::reduced_system_stage_3_kernel",
   "stage": "?",
   "time_ms": 0.014,
   "share_pct": 6.55,
   "limiter": "memory-leaning",
   "substrate": "PiM-near-bank",
   "pim_affinity": "?",
   "rationale": "quick ncu window: coarse SoL split; deep verdict joined from the studies",
   "study": {
    "attribution": {
     "shared_pct": 3.9,
     "spill_pct": 0.0,
     "global_pct": 96.1,
     "data_structure": "ba_linear_system",
     "tag_agreement_pct": 100.0
    },
    "taxonomy_stability": {
     "modal_class": "G4",
     "n_seq": "27",
     "verdict": "consistent"
    }
   },
   "evidence": {
    "dram_sol_pct": 23.255208,
    "sectors_per_req": null,
    "lfmr": null,
    "mpki": null,
    "occupancy_pct": null,
    "ai": null,
    "dominant_stall": ""
   },
   "sm_sol_pct": 5.115032,
   "roofline": null
  },
  {
   "name": "trsv_lt_exec",
   "stage": "?",
   "time_ms": 0.011,
   "share_pct": 5.44,
   "limiter": "memory-leaning",
   "substrate": "CPU/host",
   "pim_affinity": "?",
   "rationale": "quick ncu window: coarse SoL split; deep verdict joined from the studies",
   "study": {
    "attribution": {
     "shared_pct": 92.6,
     "spill_pct": 0.0,
     "global_pct": 7.4,
     "data_structure": "unmapped",
     "tag_agreement_pct": 100.0
    },
    "taxonomy_stability": {
     "modal_class": "G3",
     "n_seq": "27",
     "verdict": "consistent"
    },
    "kmeans": {
     "cluster_k8": "0",
     "sweep_best_k": "8"
    }
   },
   "evidence": {
    "dram_sol_pct": 1.483586,
    "sectors_per_req": null,
    "lfmr": null,
    "mpki": null,
    "occupancy_pct": null,
    "ai": null,
    "dominant_stall": ""
   },
   "sm_sol_pct": 0.258411,
   "roofline": null
  },
  {
   "name": "cuvslam::calc_point_update_kernel_xavier_special",
   "stage": "?",
   "time_ms": 0.009,
   "share_pct": 4.49,
   "limiter": "memory-leaning",
   "substrate": "PiM-near-bank",
   "pim_affinity": "?",
   "rationale": "quick ncu window: coarse SoL split; deep verdict joined from the studies",
   "study": {
    "attribution": {
     "shared_pct": 87.6,
     "spill_pct": 0.0,
     "global_pct": 12.4,
     "data_structure": "ba_linear_system",
     "tag_agreement_pct": 100.0
    },
    "taxonomy_stability": {
     "modal_class": "G1",
     "n_seq": "27",
     "verdict": "consistent"
    }
   },
   "evidence": {
    "dram_sol_pct": 35.963426,
    "sectors_per_req": null,
    "lfmr": null,
    "mpki": null,
    "occupancy_pct": null,
    "ai": null,
    "dominant_stall": ""
   },
   "sm_sol_pct": 35.963426,
   "roofline": null
  },
  {
   "name": "kernel",
   "stage": "?",
   "time_ms": 0.008,
   "share_pct": 3.78,
   "limiter": "memory-leaning",
   "substrate": "?",
   "pim_affinity": "?",
   "rationale": "quick ncu window: coarse SoL split; deep verdict joined from the studies",
   "study": null,
   "evidence": {
    "dram_sol_pct": 3.549757,
    "sectors_per_req": null,
    "lfmr": null,
    "mpki": null,
    "occupancy_pct": null,
    "ai": null,
    "dominant_stall": ""
   },
   "sm_sol_pct": 0.827403,
   "roofline": null
  },
  {
   "name": "cuvslam::point_term_kernel",
   "stage": "?",
   "time_ms": 0.007,
   "share_pct": 3.58,
   "limiter": "memory-leaning",
   "substrate": "PiM-scatter",
   "pim_affinity": "?",
   "rationale": "quick ncu window: coarse SoL split; deep verdict joined from the studies",
   "study": {
    "attribution": {
     "shared_pct": 1.2,
     "spill_pct": 0.0,
     "global_pct": 98.8,
     "data_structure": "ba_linear_system",
     "tag_agreement_pct": 100.0
    },
    "taxonomy_stability": {
     "modal_class": "G2",
     "n_seq": "27",
     "verdict": "consistent"
    },
    "kmeans": {
     "cluster_k8": "7",
     "sweep_best_k": "8"
    }
   },
   "evidence": {
    "dram_sol_pct": 20.930325500000002,
    "sectors_per_req": null,
    "lfmr": null,
    "mpki": null,
    "occupancy_pct": null,
    "ai": null,
    "dominant_stall": ""
   },
   "sm_sol_pct": 2.3545485,
   "roofline": null
  },
  {
   "name": "cuvslam::evaluate_cost_kernel",
   "stage": "?",
   "time_ms": 0.006,
   "share_pct": 2.7,
   "limiter": "memory-leaning",
   "substrate": "GPU+layout-fix",
   "pim_affinity": "?",
   "rationale": "quick ncu window: coarse SoL split; deep verdict joined from the studies",
   "study": {
    "attribution": {
     "shared_pct": 4.2,
     "spill_pct": 0.0,
     "global_pct": 95.8,
     "data_structure": "ba_linear_system",
     "tag_agreement_pct": 100.0
    },
    "taxonomy_stability": {
     "modal_class": "G4",
     "n_seq": "27",
     "verdict": "consistent"
    },
    "kmeans": {
     "cluster_k8": "7",
     "sweep_best_k": "8"
    }
   },
   "evidence": {
    "dram_sol_pct": 24.404762,
    "sectors_per_req": null,
    "lfmr": null,
    "mpki": null,
    "occupancy_pct": null,
    "ai": null,
    "dominant_stall": ""
   },
   "sm_sol_pct": 8.057462,
   "roofline": null
  },
  {
   "name": "cuvslam::calc_pose_update_kernel",
   "stage": "?",
   "time_ms": 0.005,
   "share_pct": 2.22,
   "limiter": "memory-leaning",
   "substrate": "CPU/host",
   "pim_affinity": "?",
   "rationale": "quick ncu window: coarse SoL split; deep verdict joined from the studies",
   "study": {
    "attribution": {
     "shared_pct": 0.0,
     "spill_pct": 0.0,
     "global_pct": 100.0,
     "data_structure": "ba_linear_system",
     "tag_agreement_pct": 100.0
    },
    "taxonomy_stability": {
     "modal_class": "G7",
     "n_seq": "27",
     "verdict": "unanimous"
    }
   },
   "evidence": {
    "dram_sol_pct": 3.133951,
    "sectors_per_req": null,
    "lfmr": null,
    "mpki": null,
    "occupancy_pct": null,
    "ai": null,
    "dominant_stall": ""
   },
   "sm_sol_pct": 0.059289,
   "roofline": null
  },
  {
   "name": "cuvslam::v1T_x_M_x_v2_kernel",
   "stage": "?",
   "time_ms": 0.003,
   "share_pct": 1.6,
   "limiter": "compute-leaning",
   "substrate": "GPU-keep",
   "pim_affinity": "?",
   "rationale": "quick ncu window: coarse SoL split; deep verdict joined from the studies",
   "study": {
    "attribution": {
     "shared_pct": 57.1,
     "spill_pct": 0.0,
     "global_pct": 42.9,
     "data_structure": "ba_linear_system",
     "tag_agreement_pct": 100.0
    },
    "taxonomy_stability": {
     "modal_class": "G7",
     "n_seq": "27",
     "verdict": "unanimous"
    }
   },
   "evidence": {
    "dram_sol_pct": 3.034712,
    "sectors_per_req": null,
    "lfmr": null,
    "mpki": null,
    "occupancy_pct": null,
    "ai": null,
    "dominant_stall": ""
   },
   "sm_sol_pct": 4.769885,
   "roofline": null
  },
  {
   "name": "cuvslam::pose_scaling_term_kernel",
   "stage": "?",
   "time_ms": 0.003,
   "share_pct": 1.54,
   "limiter": "memory-leaning",
   "substrate": "GPU-keep",
   "pim_affinity": "?",
   "rationale": "quick ncu window: coarse SoL split; deep verdict joined from the studies",
   "study": {
    "attribution": {
     "shared_pct": 34.0,
     "spill_pct": 0.0,
     "global_pct": 66.0,
     "data_structure": "ba_linear_system",
     "tag_agreement_pct": 100.0
    },
    "taxonomy_stability": {
     "modal_class": "G7",
     "n_seq": "27",
     "verdict": "unanimous"
    }
   },
   "evidence": {
    "dram_sol_pct": 0.706845,
    "sectors_per_req": null,
    "lfmr": null,
    "mpki": null,
    "occupancy_pct": null,
    "ai": null,
    "dominant_stall": ""
   },
   "sm_sol_pct": 0.211591,
   "roofline": null
  },
  {
   "name": "cuvslam::make_prediction",
   "stage": "?",
   "time_ms": 0.003,
   "share_pct": 1.48,
   "limiter": "memory-leaning",
   "substrate": "CPU/host",
   "pim_affinity": "?",
   "rationale": "quick ncu window: coarse SoL split; deep verdict joined from the studies",
   "study": {
    "attribution": {
     "shared_pct": 0.0,
     "spill_pct": 0.0,
     "global_pct": 100.0,
     "data_structure": "ba_linear_system",
     "tag_agreement_pct": 100.0
    },
    "taxonomy_stability": {
     "modal_class": "G3",
     "n_seq": "27",
     "verdict": "\u00b1G3:18/G4:9"
    }
   },
   "evidence": {
    "dram_sol_pct": 0.800781,
    "sectors_per_req": null,
    "lfmr": null,
    "mpki": null,
    "occupancy_pct": null,
    "ai": null,
    "dominant_stall": ""
   },
   "sm_sol_pct": 0.015318,
   "roofline": null
  },
  {
   "name": "dtrsv_init_up",
   "stage": "?",
   "time_ms": 0.002,
   "share_pct": 0.97,
   "limiter": "memory-leaning",
   "substrate": "CPU/host",
   "pim_affinity": "?",
   "rationale": "quick ncu window: coarse SoL split; deep verdict joined from the studies",
   "study": {
    "attribution": {
     "shared_pct": 0.0,
     "spill_pct": 0.0,
     "global_pct": 100.0,
     "data_structure": "untagged_driver",
     "tag_agreement_pct": 100.0
    },
    "taxonomy_stability": {
     "modal_class": "G7",
     "n_seq": "27",
     "verdict": "unanimous"
    }
   },
   "evidence": {
    "dram_sol_pct": 0.643382,
    "sectors_per_req": null,
    "lfmr": null,
    "mpki": null,
    "occupancy_pct": null,
    "ai": null,
    "dominant_stall": ""
   },
   "sm_sol_pct": 0.007731,
   "roofline": null
  },
  {
   "name": "xxtrf4_set_info_ker",
   "stage": "?",
   "time_ms": 0.002,
   "share_pct": 0.92,
   "limiter": "memory-leaning",
   "substrate": "CPU/host",
   "pim_affinity": "?",
   "rationale": "quick ncu window: coarse SoL split; deep verdict joined from the studies",
   "study": {
    "attribution": {
     "shared_pct": 0.0,
     "spill_pct": 0.0,
     "global_pct": 100.0,
     "data_structure": "ba_linear_system",
     "tag_agreement_pct": 100.0
    },
    "taxonomy_stability": {
     "modal_class": "G7",
     "n_seq": "27",
     "verdict": "unanimous"
    }
   },
   "evidence": {
    "dram_sol_pct": 0.61849,
    "sectors_per_req": null,
    "lfmr": null,
    "mpki": null,
    "occupancy_pct": null,
    "ai": null,
    "dominant_stall": ""
   },
   "sm_sol_pct": 0.006681,
   "roofline": null
  },
  {
   "name": "copy_info_kernel",
   "stage": "?",
   "time_ms": 0.002,
   "share_pct": 0.91,
   "limiter": "memory-leaning",
   "substrate": "CPU/host",
   "pim_affinity": "?",
   "rationale": "quick ncu window: coarse SoL split; deep verdict joined from the studies",
   "study": {
    "attribution": {
     "shared_pct": 0.0,
     "spill_pct": 0.0,
     "global_pct": 100.0,
     "data_structure": "ba_linear_system",
     "tag_agreement_pct": 100.0
    },
    "taxonomy_stability": {
     "modal_class": "G7",
     "n_seq": "27",
     "verdict": "unanimous"
    }
   },
   "evidence": {
    "dram_sol_pct": 0.61849,
    "sectors_per_req": null,
    "lfmr": null,
    "mpki": null,
    "occupancy_pct": null,
    "ai": null,
    "dominant_stall": ""
   },
   "sm_sol_pct": 0.00646,
   "roofline": null
  }
 ]
}